finder_enrichment_db_client/__init__.py
finder_enrichment_db_client/finder_enrichment_db_api_client.py
finder_enrichment_db_client-0.1.10.dist-info/METADATA
finder_enrichment_db_client-0.1.10.dist-info/WHEEL
finder_enrichment_db_client-0.1.10.dist-info/top_level.txt
finder_enrichment_db_client-0.1.10.dist-info/RECORD
