Metadata-Version: 2.4
Name: finder-enrichment-db-client
Version: 0.1.10
Summary: Client for the Finder Enrichment DB API
Author-email: Giacomo Kavanagh <giacomo.kavanagh@gmail.com>
License-Expression: MIT
Project-URL: Homepage, https://github.com/giacomokavanagh/finder-enrichment-db
Project-URL: Bug Tracker, https://github.com/giacomokavanagh/finder-enrichment-db/issues
Classifier: Programming Language :: Python :: 3.12
Requires-Python: >=3.12
Requires-Dist: pydantic>=2.0.0
Requires-Dist: fastapi>=0.104.0
Requires-Dist: httpx>=0.28.1
Requires-Dist: finder-enrichment-db-contracts>=0.1.7
